vin_ml/__init__.py
vin_ml/kernals.py
vin_ml/utils.py
vin_ml/models/NN.py
vin_ml/models/__init__.py
vin_ml/models/c4_5.py
vin_ml/models/id3.py
vin_ml/models/linear_regression.py
vin_ml/models/logistic_regression.py
vin_ml/models/perceptron.py
vin_ml/models/random_forest.py
vin_ml/models/svm.py
vin_ml-0.1.dist-info/METADATA
vin_ml-0.1.dist-info/WHEEL
vin_ml-0.1.dist-info/top_level.txt
vin_ml-0.1.dist-info/RECORD
