Metadata-Version: 2.1
Name: vin-ml
Version: 0.1
Summary: My ML Lab Codes
Home-page: https://github.com/Vinayak-sophos/vin_ml
Author: Vinayak Sachdeva
Author-email: vishusachdeva228@gmail.com
License: UNKNOWN
Platform: UNKNOWN
Classifier: Programming Language :: Python :: 3
Classifier: Operating System :: OS Independent
